MANIFEST.in
setup.py
iitg_acad_hub/.download.txt
iitg_acad_hub/.info.txt
iitg_acad_hub/__init__.py
iitg_acad_hub/bookLending.py
iitg_acad_hub/command_line.py
iitg_acad_hub/details.py
iitg_acad_hub/exam.py
iitg_acad_hub/libSearch.py
iitg_acad_hub/notes.py
iitg_acad_hub/project.py
iitg_acad_hub/tools.py
iitg_acad_hub/webcrawler.py
iitg_acad_hub.egg-info/PKG-INFO
iitg_acad_hub.egg-info/SOURCES.txt
iitg_acad_hub.egg-info/dependency_links.txt
iitg_acad_hub.egg-info/entry_points.txt
iitg_acad_hub.egg-info/not-zip-safe
iitg_acad_hub.egg-info/requires.txt
iitg_acad_hub.egg-info/top_level.txt
iitg_acad_hub/icons/3dm-file-format.png
iitg_acad_hub/icons/3ds-file-format-symbol.png
iitg_acad_hub/icons/3g2-file-format-symbol.png
iitg_acad_hub/icons/3gp-file-format-variant.png
iitg_acad_hub/icons/7z-file-format-variant.png
iitg_acad_hub/icons/aac-file-format.png
iitg_acad_hub/icons/ai-file-format-symbol.png
iitg_acad_hub/icons/aif-file-format.png
iitg_acad_hub/icons/angel.png
iitg_acad_hub/icons/apk-file-format.png
iitg_acad_hub/icons/app-file-format-variant.png
iitg_acad_hub/icons/asf-file-format-variant.png
iitg_acad_hub/icons/asp-file-format-symbol.png
iitg_acad_hub/icons/aspx-file-format.png
iitg_acad_hub/icons/asx-multimedia-file-format.png
iitg_acad_hub/icons/avi-file-format-variant.png
iitg_acad_hub/icons/bak-file-format-symbol.png
iitg_acad_hub/icons/bat-file-format-symbol.png
iitg_acad_hub/icons/bin-file-format.png
iitg_acad_hub/icons/blank-file.png
iitg_acad_hub/icons/bmp-file-format-symbol.png
iitg_acad_hub/icons/cab-file-format.png
iitg_acad_hub/icons/cad-file-format-symbol.png
iitg_acad_hub/icons/cdr-file-format-symbol.png
iitg_acad_hub/icons/cer-file-format.png
iitg_acad_hub/icons/cfg-file-format-symbol.png
iitg_acad_hub/icons/cfm-file-format-symbol.png
iitg_acad_hub/icons/cgi-file-format-symbol.png
iitg_acad_hub/icons/class-file-format-variant.png
iitg_acad_hub/icons/com-file-format-symbol.png
iitg_acad_hub/icons/cpl-file-format-variant.png
iitg_acad_hub/icons/cpp-file-format-symbol.png
iitg_acad_hub/icons/crx-file-format-symbol.png
iitg_acad_hub/icons/csr-file-format.png
iitg_acad_hub/icons/css-file-format-symbol.png
iitg_acad_hub/icons/csv-file-format-symbol.png
iitg_acad_hub/icons/cue-file-format-symbol.png
