Metadata-Version: 1.1
Name: iitg-acad-hub
Version: 2.4.3
Summary: Acad Hub for IIT Guwahati
Home-page: UNKNOWN
Author: team10cs243
Author-email: UNKNOWN
License: GPLv3
Keywords: acad hub iitg iit books pdf lend
Platform: UNKNOWN
Classifier: Development Status :: 4 - Beta
Classifier: Programming Language :: Python :: 2.7
Classifier: License :: OSI Approved :: GNU General Public License v3 or later (GPLv3+)
Classifier: Natural Language :: English
Classifier: Operating System :: POSIX :: Linux
